llm_optimizer/__init__.py
llm_optimizer/main.py
llm_optimizer-0.1.6.dist-info/LICENCE
llm_optimizer-0.1.6.dist-info/METADATA
llm_optimizer-0.1.6.dist-info/WHEEL
llm_optimizer-0.1.6.dist-info/entry_points.txt
llm_optimizer-0.1.6.dist-info/top_level.txt
llm_optimizer-0.1.6.dist-info/RECORD
