Metadata-Version: 2.1
Name: llm-optimizer
Version: 0.1.6
Summary: Optimize LLM outputs and track emissions
Home-page: https://github.com/viji123450/llm_optimizer
Author: Vijayalakshmi
Author-email: viji814881@email.com
License: MIT
Classifier: Programming Language :: Python :: 3
Classifier: Operating System :: OS Independent
Requires-Python: >=3.8
License-File: LICENCE
Requires-Dist: torch
Requires-Dist: transformers
Requires-Dist: codecarbon
Requires-Dist: evaluate
Requires-Dist: numpy
Requires-Dist: rouge-score
Requires-Dist: nltk
Requires-Dist: absl-py
